alkivi/__init__.py
alkivi/logger/__init__.py
alkivi/logger/handlers.py
alkivi/logger/logger.py
alkivi/logger/version.py
alkivi_logger-1.6.0.dist-info/LICENSE
alkivi_logger-1.6.0.dist-info/METADATA
alkivi_logger-1.6.0.dist-info/WHEEL
alkivi_logger-1.6.0.dist-info/top_level.txt
alkivi_logger-1.6.0.dist-info/RECORD
