Metadata-Version: 2.1
Name: alkivi-logger
Version: 1.6.0
Summary: Python logger used at Alkivi
Home-page: https://github.com/alkivi-sas/python-alkivi-logger
Author: Anthony Martinet
Author-email: anthony@alkivi.fr
License: LGPLv3
Keywords: alkivi logger
Classifier: Development Status :: 4 - Beta
Classifier: Environment :: Console
Classifier: Intended Audience :: Developers
Classifier: Topic :: Software Development :: Build Tools
Classifier: License :: OSI Approved :: GNU Lesser General Public License v3 (LGPLv3)
Classifier: Programming Language :: Python :: 2
Classifier: Programming Language :: Python :: 2.7
Classifier: Programming Language :: Python :: 3
Classifier: Programming Language :: Python :: 3.2
Classifier: Programming Language :: Python :: 3.3
Classifier: Programming Language :: Python :: 3.4
Classifier: Programming Language :: Python :: 3.5
License-File: LICENSE
Provides-Extra: dev
Provides-Extra: test
